pyMd2Doc-2.0.2.dist-info/DESCRIPTION.rst
pyMd2Doc-2.0.2.dist-info/METADATA
pyMd2Doc-2.0.2.dist-info/RECORD
pyMd2Doc-2.0.2.dist-info/WHEEL
pyMd2Doc-2.0.2.dist-info/metadata.json
pyMd2Doc-2.0.2.dist-info/top_level.txt
pymd2doc/__init__.py
pymd2doc/createDoc.py
pymd2doc/test.py
