Metadata-Version: 2.0
Name: pyMd2Doc
Version: 2.0.2
Summary: fix bug
Home-page: https://github.com/yuleMeng/pyMd2Doc
Author: Yule Meng
Author-email: 88914511@qq.com
License: MIT
Platform: UNKNOWN
Classifier: Environment :: Web Environment
Classifier: Intended Audience :: Developers
Classifier: Operating System :: OS Independent
Classifier: Topic :: Text Processing :: Indexing
Classifier: Topic :: Utilities
Classifier: Topic :: Internet
Classifier: Topic :: Software Development :: Libraries :: Python Modules
Classifier: Programming Language :: Python
Classifier: Programming Language :: Python :: 3
Requires-Dist: Markdown
